[
    {
        "id": 1,
        "name": "Ciro",
        "employeed_id": "43h1781h3871h38171",
        "updated_at": "2024-01-24T19:09:36.440580Z",
        "created_at": "2024-01-24T19:09:36.440332Z"
    },
    {
        "id": 2,
        "name": "Marcos",
        "employeed_id": "5h1781h3871h38171",
        "updated_at": "2024-01-24T19:09:36.440580Z",
        "created_at": "2024-01-24T19:09:36.440332Z"
    },
    {
        "id": 3,
        "name": "Letícia",
        "employeed_id": "3h1781h3871h38171",
        "updated_at": "2024-01-24T19:09:36.440580Z",
        "created_at": "2024-01-24T19:09:36.440332Z"
    }
]